flowmelet/__init__.py
flowmelet/main.py
flowmelet/core/__init__.py
flowmelet/core/stages.py
flowmelet/core/system_tree.py
flowmelet/core/utils.py
flowmelet/static/lineage.png
flowmelet/templates/DAGFactoryTemplate.py
flowmelet/templates/DAGTemplate.py
flowmelet/templates/ExternalTaskSensorTemplate.yml
flowmelet/templates/LineageTemplate.html
flowmelet-0.0.10.dist-info/LICENSE
flowmelet-0.0.10.dist-info/METADATA
flowmelet-0.0.10.dist-info/WHEEL
flowmelet-0.0.10.dist-info/entry_points.txt
flowmelet-0.0.10.dist-info/top_level.txt
flowmelet-0.0.10.dist-info/RECORD
