Metadata-Version: 2.1
Name: flowmelet
Version: 0.0.10
Summary: Flowmelet - Airflow DAG Compile-time Generator with unified features from Airflow, dagfactor, Gusty, and DBT
Home-page: https://github.com/yhow101/flowmelet.git
Author: yhow
Author-email: yhow11@gmail.com
Classifier: Development Status :: 3 - Alpha
Classifier: Intended Audience :: Developers
Classifier: License :: OSI Approved :: Apache Software License
Requires-Python: >=3.6
License-File: LICENSE
Requires-Dist: apache-airflow
Requires-Dist: Jinja2
Requires-Dist: PyYAML
Requires-Dist: argparse
